dissect/clfs/__init__.py
dissect/clfs/blf.py
dissect/clfs/c_clfs.py
dissect/clfs/container.py
dissect/clfs/exceptions.py
dissect.clfs-1.9.dist-info/COPYRIGHT
dissect.clfs-1.9.dist-info/LICENSE
dissect.clfs-1.9.dist-info/METADATA
dissect.clfs-1.9.dist-info/WHEEL
dissect.clfs-1.9.dist-info/top_level.txt
dissect.clfs-1.9.dist-info/RECORD
