Metadata-Version: 2.1
Name: dissect.clfs
Version: 1.9
Summary: A Dissect module implementing a parser for the CLFS (Common Log File System) file system of Windows
Author-email: Dissect Team <dissect@fox-it.com>
License: Affero General Public License v3
Project-URL: homepage, https://dissect.tools
Project-URL: documentation, https://docs.dissect.tools/en/latest/projects/dissect.clfs
Project-URL: repository, https://github.com/fox-it/dissect.clfs
Classifier: Development Status :: 5 - Production/Stable
Classifier: Environment :: Console
Classifier: Intended Audience :: Developers
Classifier: Intended Audience :: Information Technology
Classifier: License :: OSI Approved
Classifier: Operating System :: OS Independent
Classifier: Programming Language :: Python :: 3
Classifier: Topic :: Internet :: Log Analysis
Classifier: Topic :: Scientific/Engineering :: Information Analysis
Classifier: Topic :: Security
Classifier: Topic :: Utilities
Requires-Python: ~=3.9
License-File: LICENSE
License-File: COPYRIGHT
Requires-Dist: dissect.cstruct <5,>=4
Provides-Extra: dev
Requires-Dist: dissect.cstruct <5.0.dev,>=4.0.dev ; extra == 'dev'
